hawkinsdb/__init__.py
hawkinsdb/base.py
hawkinsdb/config.py
hawkinsdb/core.py
hawkinsdb/enrichment.py
hawkinsdb/llm_interface.py
hawkinsdb/openai_interface.py
hawkinsdb/py.typed
hawkinsdb/types.py
hawkinsdb/storage/__init__.py
hawkinsdb/storage/sqlite.py
hawkinsdb-1.0.2.dist-info/METADATA
hawkinsdb-1.0.2.dist-info/WHEEL
hawkinsdb-1.0.2.dist-info/top_level.txt
hawkinsdb-1.0.2.dist-info/RECORD
