Metadata-Version: 2.2
Name: hawkinsdb
Version: 1.0.2
Summary: A neuroscience-inspired memory layer for LLM applications
Author-email: Harish Santhanalakshmi Ganesan <hawkinsdb@example.com>
Project-URL: Homepage, https://github.com/harishsg993010/HawkinsDB
Project-URL: Documentation, https://github.com/harishsg993010/HawkinsDB/tree/main/docs
Project-URL: Repository, https://github.com/harishsg993010/HawkinsDB.git
Project-URL: Issues, https://github.com/harishsg993010/HawkinsDB/issues
Classifier: Development Status :: 3 - Alpha
Classifier: Intended Audience :: Developers
Classifier: Intended Audience :: Science/Research
Classifier: License :: OSI Approved :: MIT License
Classifier: Operating System :: OS Independent
Classifier: Programming Language :: Python :: 3 :: Only
Classifier: Programming Language :: Python :: 3.10
Classifier: Programming Language :: Python :: 3.11
Classifier: Topic :: Database
Classifier: Topic :: Scientific/Engineering :: Artificial Intelligence
Classifier: Topic :: Software Development :: Libraries :: Python Modules
Classifier: Typing :: Typed
Requires-Python: >=3.11
Requires-Dist: litellm>=1.61.6
Requires-Dist: tenacity>=8.0.0
Requires-Dist: setuptools>=75.8.0
Requires-Dist: mock>=5.1.0
Requires-Dist: unittest-xml-reporting>=3.2.0
Requires-Dist: openai>=1.63.2
Requires-Dist: trafilatura>=2.0.0
Requires-Dist: twilio>=9.4.5
Requires-Dist: lxml>=5.3.1
Requires-Dist: build>=1.2.2.post1
Requires-Dist: twine>=6.1.0
Provides-Extra: dev
Requires-Dist: pytest>=7.0.0; extra == "dev"
Requires-Dist: pytest-cov>=4.1.0; extra == "dev"
Requires-Dist: pytest-asyncio>=0.23.0; extra == "dev"
Requires-Dist: black>=23.0.0; extra == "dev"
Requires-Dist: isort>=5.12.0; extra == "dev"
Requires-Dist: mypy>=1.0.0; extra == "dev"
Requires-Dist: ruff>=0.1.0; extra == "dev"
Provides-Extra: docs
Requires-Dist: sphinx>=7.0.0; extra == "docs"
Requires-Dist: sphinx-rtd-theme>=1.3.0; extra == "docs"
Requires-Dist: myst-parser>=2.0.0; extra == "docs"
Provides-Extra: conceptnet
Requires-Dist: networkx>=3.0.0; extra == "conceptnet"
Requires-Dist: requests-cache>=1.1.0; extra == "conceptnet"
Provides-Extra: llm
Requires-Dist: openai>=1.0.0; extra == "llm"
Requires-Dist: tenacity>=8.2.0; extra == "llm"
Requires-Dist: tiktoken>=0.5.0; extra == "llm"
Provides-Extra: all
Requires-Dist: networkx>=3.0.0; extra == "all"
Requires-Dist: requests-cache>=1.1.0; extra == "all"
Requires-Dist: openai>=1.0.0; extra == "all"
Requires-Dist: tenacity>=8.2.0; extra == "all"
Requires-Dist: tiktoken>=0.5.0; extra == "all"
